{"z":14,"x":6354,"y":9138,"features":[{"k":"c","i":"c-14-25416-36552","x":-40.383053,"y":-20.34866,"p":2,"b":[-40.383536,-20.349408,-40.382571,-20.347911]},{"k":"c","i":"c-14-25419-36555","x":-40.368286,"y":-20.361453,"p":3,"b":[-40.3688,-20.362211,-40.36764,-20.360876]},{"k":"s","i":"school-433","x":-40.366293,"y":-20.355234,"n":"school-433","d":"cariacica"},{"k":"s","i":"school-459","x":-40.378397,"y":-20.347817,"n":"school-459","d":"cariacica"},{"k":"s","i":"school-467","x":-40.379174,"y":-20.355533,"n":"school-467","d":"cariacica"},{"k":"s","i":"school-483","x":-40.366189,"y":-20.352241,"n":"school-483","d":"cariacica"},{"k":"s","i":"school-486","x":-40.38323,"y":-20.35494,"n":"school-486","d":"cariacica"}]}