{"shard":"laranja-da-terra","schools":{"escolas_municipais_es_32070420":{"id":"escolas_municipais_es_32070420","inep_code":"32070420","name":"CEMEI CATATAU","municipio":"Laranja da Terra","uf":"ES","status":"Em Atividade","address":"RUA OTTO MAIER, S/N","number":"S/N","postal_code":"29615-000","classification":"alta","georef_source":"INEP Tabela_Escola_2025.csv"},"escolas_municipais_es_32029705":{"id":"escolas_municipais_es_32029705","inep_code":"32029705","name":"CEMEI EMILIO JASKE","municipio":"Laranja da Terra","uf":"ES","status":"Em Atividade","address":"LOCALIDADE JOATUBA","postal_code":"29617-000","classification":"alta","georef_source":"INEP Tabela_Escola_2025.csv"},"escolas_municipais_es_32082932":{"id":"escolas_municipais_es_32082932","inep_code":"32082932","name":"CEMEI KAYKE PRUDENTE MERCANDELE","municipio":"Laranja da Terra","uf":"ES","status":"Em Atividade","address":"RUA PRINCIPAL, SN","number":"SN","postal_code":"29619-000","classification":"alta","georef_source":"INEP Tabela_Escola_2025.csv"},"escolas_municipais_es_32029799":{"id":"escolas_municipais_es_32029799","inep_code":"32029799","name":"EMEF JOAO VALIM","municipio":"Laranja da Terra","uf":"ES","status":"Em Atividade","address":"RUA PRINCIPAL, S/N","number":"S/N","postal_code":"29619-000","classification":"alta","georef_source":"INEP Tabela_Escola_2025.csv"},"escolas_municipais_es_32029551":{"id":"escolas_municipais_es_32029551","inep_code":"32029551","name":"EMEFTI CINCO PONTOES","municipio":"Laranja da Terra","uf":"ES","status":"Em Atividade","address":"LOCALIDADE CINCO PONTOES","postal_code":"29617-000","classification":"alta","georef_source":"INEP Tabela_Escola_2025.csv"},"escolas_municipais_es_32029870":{"id":"escolas_municipais_es_32029870","inep_code":"32029870","name":"EMEFTI CORREGO ADAME","municipio":"Laranja da Terra","uf":"ES","status":"Em Atividade","address":"CORREGO ADAME, 000","number":"000","postal_code":"29619-000","classification":"alta","georef_source":"INEP Tabela_Escola_2025.csv"},"escolas_municipais_es_32029780":{"id":"escolas_municipais_es_32029780","inep_code":"32029780","name":"EMEFTI UNIAO LARANJENSE","municipio":"Laranja da Terra","uf":"ES","status":"Em Atividade","address":"PRACA CARLOS TESCH, SN, ESCOLA","number":"SN","postal_code":"29615-000","classification":"alta","georef_source":"INEP Tabela_Escola_2025.csv"},"escolas_municipais_es_32029837":{"id":"escolas_municipais_es_32029837","inep_code":"32029837","name":"EMEIEFTI BARRA DO JEQUITIBA","municipio":"Laranja da Terra","uf":"ES","status":"Em Atividade","address":"BARRA DO JEQUITIBA","postal_code":"29619-000","classification":"alta","georef_source":"INEP Tabela_Escola_2025.csv"},"escolas_municipais_es_32029624":{"id":"escolas_municipais_es_32029624","inep_code":"32029624","name":"EMEIEFTI CORREGO DA TABUA","municipio":"Laranja da Terra","uf":"ES","status":"Em Atividade","address":"LOCALIDADE MATUTINA","postal_code":"29617-000","classification":"alta","georef_source":"INEP Tabela_Escola_2025.csv"},"escolas_municipais_es_32029578":{"id":"escolas_municipais_es_32029578","inep_code":"32029578","name":"EMEIEFTI FAZENDA ALBERTO LITTIG","municipio":"Laranja da Terra","uf":"ES","status":"Em Atividade","address":"LOCALIDADE PICADAO","postal_code":"29617-000","classification":"alta","georef_source":"INEP Tabela_Escola_2025.csv"},"escolas_municipais_es_32029748":{"id":"escolas_municipais_es_32029748","inep_code":"32029748","name":"EMEIEFTI FAZENDA CARLOS FICK","municipio":"Laranja da Terra","uf":"ES","status":"Em Atividade","address":"CRISCIUMA","postal_code":"29619-000","classification":"alta","georef_source":"INEP Tabela_Escola_2025.csv"},"escolas_municipais_es_32029667":{"id":"escolas_municipais_es_32029667","inep_code":"32029667","name":"EMEIEFTI FELIZ DESTINO","municipio":"Laranja da Terra","uf":"ES","status":"Em Atividade","address":"LOCALIDADE BARRA DO TAQUARAL","postal_code":"29617-000","classification":"alta","georef_source":"INEP Tabela_Escola_2025.csv"},"escolas_municipais_es_32029586":{"id":"escolas_municipais_es_32029586","inep_code":"32029586","name":"EMEIEFTI LARANJA DA TERRA","municipio":"Laranja da Terra","uf":"ES","status":"Em Atividade","address":"RUA GUILHERME SEIBEL","postal_code":"29615-000","classification":"alta","georef_source":"INEP Tabela_Escola_2025.csv"},"escolas_municipais_es_32029519":{"id":"escolas_municipais_es_32029519","inep_code":"32029519","name":"EMEIEFTI NOBERTO KLUG","municipio":"Laranja da Terra","uf":"ES","status":"Em Atividade","address":"LOCALIDADE BARRA DA PERDIDA, 000","number":"000","postal_code":"29615-000","classification":"alta","georef_source":"INEP Tabela_Escola_2025.csv"},"escolas_municipais_es_32029675":{"id":"escolas_municipais_es_32029675","inep_code":"32029675","name":"EMEIEFTI RIO GRANDE","municipio":"Laranja da Terra","uf":"ES","status":"Em Atividade","address":"RUA PRINCIPAL, 00","number":"00","postal_code":"29619-000","classification":"alta","georef_source":"INEP Tabela_Escola_2025.csv"},"escolas_municipais_es_32029420":{"id":"escolas_municipais_es_32029420","inep_code":"32029420","name":"EMEIEFTI VALENTIM PEROZINI","municipio":"Laranja da Terra","uf":"ES","status":"Em Atividade","address":"LOCALIDADE SAO LUIZ DE MIRANDA","postal_code":"29615-000","classification":"alta","georef_source":"INEP Tabela_Escola_2025.csv"}}}