{"shard":"linhares","schools":{"escolas_municipais_es_32022603":{"id":"escolas_municipais_es_32022603","inep_code":"32022603","name":"CEIM ADAGMAR PINTO SANTOS","municipio":"Linhares","uf":"ES","status":"Em Atividade","address":"DOM PEDRO II, S/N, INTERLAGOS","number":"S/N","district":"INTERLAGOS","postal_code":"29903-200","classification":"alta","georef_source":"INEP Tabela_Escola_2025.csv"},"escolas_municipais_es_32022620":{"id":"escolas_municipais_es_32022620","inep_code":"32022620","name":"CEIM AGNELO GUIMARAES","municipio":"Linhares","uf":"ES","status":"Em Atividade","address":"JOSE TESCH, 1010, COLINA","number":"1010","district":"COLINA","postal_code":"29900-397","classification":"alta","georef_source":"INEP Tabela_Escola_2025.csv"},"escolas_municipais_es_32078862":{"id":"escolas_municipais_es_32078862","inep_code":"32078862","name":"CEIM AGOSTINHO RIGONI","municipio":"Linhares","uf":"ES","status":"Em Atividade","address":"RUA SIRI, S/N, PONTAL DO IPIRANGA","number":"S/N","district":"PONTAL DO IPIRANGA","postal_code":"29919-250","classification":"alta","georef_source":"INEP Tabela_Escola_2025.csv"},"escolas_municipais_es_32064497":{"id":"escolas_municipais_es_32064497","inep_code":"32064497","name":"CEIM ALEGRIA DO SABER","municipio":"Linhares","uf":"ES","status":"Em Atividade","address":"ADEMAR LUIZ PIANA, S/N, SANTA CRUZ","number":"S/N","district":"SANTA CRUZ","postal_code":"29908-034","classification":"alta","georef_source":"INEP Tabela_Escola_2025.csv"},"escolas_municipais_es_32024932":{"id":"escolas_municipais_es_32024932","inep_code":"32024932","name":"CEIM ALFREDO CHRIST","municipio":"Linhares","uf":"ES","status":"Em Atividade","address":"RURAL, S/N, AREA RURAL DE LINHARES","number":"S/N","district":"AREA RURAL DE LINHARES","postal_code":"29918-899","classification":"alta","georef_source":"INEP Tabela_Escola_2025.csv"},"escolas_municipais_es_32066910":{"id":"escolas_municipais_es_32066910","inep_code":"32066910","name":"CEIM AMIGOS DO SABER","municipio":"Linhares","uf":"ES","status":"Em Atividade","address":"ODILON NUNES BARROSO, SN, PLANALTO","number":"SN","district":"PLANALTO","postal_code":"29906-470","classification":"alta","georef_source":"INEP Tabela_Escola_2025.csv"},"escolas_municipais_es_32070349":{"id":"escolas_municipais_es_32070349","inep_code":"32070349","name":"CEIM ANGELINA SCANDIAN RIGONI","municipio":"Linhares","uf":"ES","status":"Em Atividade","address":"CEDRO, SN, 00, MOVELAR","number":"SN","district":"MOVELAR","postal_code":"29906-170","classification":"alta","georef_source":"INEP Tabela_Escola_2025.csv"},"escolas_municipais_es_32022638":{"id":"escolas_municipais_es_32022638","inep_code":"32022638","name":"CEIM ANTONIO APRIGIO","municipio":"Linhares","uf":"ES","status":"Em Atividade","address":"SAO PAULO, SN, AVISO","number":"SN","district":"AVISO","postal_code":"29901-150","classification":"alta","georef_source":"INEP Tabela_Escola_2025.csv"},"escolas_municipais_es_32067674":{"id":"escolas_municipais_es_32067674","inep_code":"32067674","name":"CEIM ARISTIDES PINTO CALDEIRA","municipio":"Linhares","uf":"ES","status":"Em Atividade","address":"GUANABARA, SN, AVISO","number":"SN","district":"AVISO","postal_code":"29901-160","classification":"alta","georef_source":"INEP Tabela_Escola_2025.csv"},"escolas_municipais_es_32022654":{"id":"escolas_municipais_es_32022654","inep_code":"32022654","name":"CEIM BRANCA DE NEVE","municipio":"Linhares","uf":"ES","status":"Em Atividade","address":"DOS JASMINS, 323, JARDIM LAGUNA","number":"323","district":"JARDIM LAGUNA","postal_code":"29904-340","classification":"alta","georef_source":"INEP Tabela_Escola_2025.csv"},"escolas_municipais_es_32022662":{"id":"escolas_municipais_es_32022662","inep_code":"32022662","name":"CEIM CHAPEUZINHO VERMELHO","municipio":"Linhares","uf":"ES","status":"Em Atividade","address":"QUINTINO BOCAIUVA, 1217, INTERLAGOS","number":"1217","district":"INTERLAGOS","postal_code":"29903-059","classification":"alta","georef_source":"INEP Tabela_Escola_2025.csv"},"escolas_municipais_es_32073925":{"id":"escolas_municipais_es_32073925","inep_code":"32073925","name":"CEIM CRESCER","municipio":"Linhares","uf":"ES","status":"Em Atividade","address":"PINHEIROS, S/N, INTERLAGOS","number":"S/N","district":"INTERLAGOS","postal_code":"29903-053","classification":"alta","georef_source":"INEP Tabela_Escola_2025.csv"},"escolas_municipais_es_32022913":{"id":"escolas_municipais_es_32022913","inep_code":"32022913","name":"CEIM DOCE MEL","municipio":"Linhares","uf":"ES","status":"Em Atividade","address":"LAGOA DO AGUIAR, S/N, BAIXO QUARTEL","number":"S/N","district":"BAIXO QUARTEL","postal_code":"29913-400","classification":"alta","georef_source":"INEP Tabela_Escola_2025.csv"},"escolas_municipais_es_32066961":{"id":"escolas_municipais_es_32066961","inep_code":"32066961","name":"CEIM ENOCK DE FREITAS","municipio":"Linhares","uf":"ES","status":"Em Atividade","address":"PRESIDENTE RODRIGUES ALVES, S/Nº, JUPARANA","number":"S/Nº","district":"JUPARANA","postal_code":"29900-595","classification":"alta","georef_source":"INEP Tabela_Escola_2025.csv"},"escolas_municipais_es_32078013":{"id":"escolas_municipais_es_32078013","inep_code":"32078013","name":"CEIM GENY RIBEIRO DE SOUZA","municipio":"Linhares","uf":"ES","status":"Em Atividade","address":"IBIRACU, S/N, SHELL","number":"S/N","district":"SHELL","postal_code":"29901-510","classification":"alta","georef_source":"INEP Tabela_Escola_2025.csv"},"escolas_municipais_es_32081464":{"id":"escolas_municipais_es_32081464","inep_code":"32081464","name":"CEIM GIOVANI PAULO SALVADOR MEIRA","municipio":"Linhares","uf":"ES","status":"Em Atividade","address":"PEDRO GAMA, SN, PROXIMO A BR 101, CANIVETE","number":"SN","district":"CANIVETE","postal_code":"29909-180","classification":"alta","georef_source":"INEP Tabela_Escola_2025.csv"},"escolas_municipais_es_32067984":{"id":"escolas_municipais_es_32067984","inep_code":"32067984","name":"CEIM ILIDIA ROSA DE ALMEIDA DOS SANTOS","municipio":"Linhares","uf":"ES","status":"Em Atividade","address":"AMAPA, 1558, INTERLAGOS","number":"1558","district":"INTERLAGOS","postal_code":"29903-650","classification":"alta","georef_source":"INEP Tabela_Escola_2025.csv"},"escolas_municipais_es_32023375":{"id":"escolas_municipais_es_32023375","inep_code":"32023375","name":"CEIM JEAN CARLOS BASTOS","municipio":"Linhares","uf":"ES","status":"Em Atividade","address":"GERALDO BOBBIO, S/N, RUA PRINCIPAL, GUAXE","number":"S/N","district":"GUAXE","postal_code":"29911-200","classification":"alta","georef_source":"INEP Tabela_Escola_2025.csv"},"escolas_municipais_es_32083025":{"id":"escolas_municipais_es_32083025","inep_code":"32083025","name":"CEIM JOCAFE","municipio":"Linhares","uf":"ES","status":"Em Atividade","address":"SEBASTIAO JOSE FERREIRA, SN, RESIDENCIAL JOCAFE, SANTA CRUZ","number":"SN","district":"SANTA CRUZ","postal_code":"29908-205","classification":"alta","georef_source":"INEP Tabela_Escola_2025.csv"},"escolas_municipais_es_32083505":{"id":"escolas_municipais_es_32083505","inep_code":"32083505","name":"CEIM JOELMA ROCHA VIEIRA","municipio":"Linhares","uf":"ES","status":"Em Atividade","address":"BENEVENUTO ZORZANELLI, S/N, PROXIMO AO COMPLEXO, BEBEDOURO","number":"S/N","district":"BEBEDOURO","postal_code":"29913-030","classification":"media","georef_source":"google_geocoding_api"},"escolas_municipais_es_32064527":{"id":"escolas_municipais_es_32064527","inep_code":"32064527","name":"CEIM JOSE CANDIDO DURAO","municipio":"Linhares","uf":"ES","status":"Em Atividade","address":"JOAO BONICENHA, SN, Q 36, SÃO JOSÉ","number":"SN","district":"SÃO JOSÉ","postal_code":"29905-110","classification":"alta","georef_source":"INEP Tabela_Escola_2025.csv"},"escolas_municipais_es_32064845":{"id":"escolas_municipais_es_32064845","inep_code":"32064845","name":"CEIM JOSE ELIAS","municipio":"Linhares","uf":"ES","status":"Em Atividade","address":"AURORA NUNES DE OLIVEIRA, SN, LINHARES V","number":"SN","district":"LINHARES V","postal_code":"29905-320","classification":"alta","georef_source":"INEP Tabela_Escola_2025.csv"},"escolas_municipais_es_32066929":{"id":"escolas_municipais_es_32066929","inep_code":"32066929","name":"CEIM LEODOVICO DONATELLI","municipio":"Linhares","uf":"ES","status":"Em Atividade","address":"AVENIDA BENEVENUTO ZORZANELLI, S/N, BEBEDOURO","number":"S/N","district":"BEBEDOURO","postal_code":"29913-030","classification":"alta","georef_source":"INEP Tabela_Escola_2025.csv"},"escolas_municipais_es_32022697":{"id":"escolas_municipais_es_32022697","inep_code":"32022697","name":"CEIM MANOEL FARIAS DE SOUZA","municipio":"Linhares","uf":"ES","status":"Em Atividade","address":"GOVERNADOR DIAS LOPES, SN, NOVO HORIZONTE","number":"SN","district":"NOVO HORIZONTE","postal_code":"29902-060","classification":"alta","georef_source":"INEP Tabela_Escola_2025.csv"},"escolas_municipais_es_32080573":{"id":"escolas_municipais_es_32080573","inep_code":"32080573","name":"CEIM MARIANA BATISTA POMPERMAYER","municipio":"Linhares","uf":"ES","status":"Em Atividade","address":"DOMINGOS BELIZARIO, S/N, SANTA CRUZ","number":"S/N","district":"SANTA CRUZ","postal_code":"29908-360","classification":"alta","georef_source":"INEP Tabela_Escola_2025.csv"},"escolas_municipais_es_32067780":{"id":"escolas_municipais_es_32067780","inep_code":"32067780","name":"CEIM OLGA BORTOT MOLINA","municipio":"Linhares","uf":"ES","status":"Em Atividade","address":"OLGA BORTOT MOLINA, S/N, CANIVETE","number":"S/N","district":"CANIVETE","postal_code":"29909-210","classification":"alta","georef_source":"INEP Tabela_Escola_2025.csv"},"escolas_municipais_es_32077467":{"id":"escolas_municipais_es_32077467","inep_code":"32077467","name":"CEIM PERPETUA MARIA DOS ANJOS","municipio":"Linhares","uf":"ES","status":"Em Atividade","address":"AV. MACHADO DE ASSIS, S/N, PALMITAL","number":"S/N","district":"PALMITAL","postal_code":"29906-885","classification":"alta","georef_source":"INEP Tabela_Escola_2025.csv"},"escolas_municipais_es_32083157":{"id":"escolas_municipais_es_32083157","inep_code":"32083157","name":"CEIM PROFESSORA ANGELA MARIA GIOVANELI","municipio":"Linhares","uf":"ES","status":"Em Atividade","address":"ARTUR PINTO SANTANA, 577, CEIM, INTERLAGOS","number":"577","district":"INTERLAGOS","postal_code":"29903-280","classification":"media","georef_source":"google_geocoding_api"},"escolas_municipais_es_32070330":{"id":"escolas_municipais_es_32070330","inep_code":"32070330","name":"CEIM REINO MAGICO","municipio":"Linhares","uf":"ES","status":"Em Atividade","address":"JOAQUIM BATISTA DUARTE, 55, NOVA BETÂNIA","number":"55","district":"NOVA BETÂNIA","postal_code":"29907-540","classification":"alta","georef_source":"INEP Tabela_Escola_2025.csv"},"escolas_municipais_es_32083017":{"id":"escolas_municipais_es_32083017","inep_code":"32083017","name":"CEIM RIO DOCE","municipio":"Linhares","uf":"ES","status":"Em Atividade","address":"AVENIDA JOSE TURI, S/N, RESIDENCIAL RIO DOCE, AVISO","number":"S/N","district":"AVISO","postal_code":"29901-381","classification":"media","georef_source":"google_geocoding_api"},"escolas_municipais_es_32064500":{"id":"escolas_municipais_es_32064500","inep_code":"32064500","name":"CEIM SANTA RITA DE CASSIA","municipio":"Linhares","uf":"ES","status":"Em Atividade","address":"RUA PRESIDENTE DEODORO DA FONSECA, S/N, ARACA","number":"S/N","district":"ARACA","postal_code":"29901-415","classification":"alta","georef_source":"INEP Tabela_Escola_2025.csv"},"escolas_municipais_es_32022930":{"id":"escolas_municipais_es_32022930","inep_code":"32022930","name":"CEIM SEBASTIAO JUSTINO FURTADO","municipio":"Linhares","uf":"ES","status":"Em Atividade","address":"SANTA LUZIA, SN, RIO QUARTEL","number":"SN","district":"RIO QUARTEL","postal_code":"29913-315","classification":"alta","georef_source":"INEP Tabela_Escola_2025.csv"},"escolas_municipais_es_32083009":{"id":"escolas_municipais_es_32083009","inep_code":"32083009","name":"CEIM THEREZINHA DURAO COSTA","municipio":"Linhares","uf":"ES","status":"Em Atividade","address":"JATOBA, SN, TRÊS BARRAS","number":"SN","district":"TRÊS BARRAS","postal_code":"29907-312","classification":"alta","georef_source":"INEP Tabela_Escola_2025.csv"},"escolas_municipais_es_32070322":{"id":"escolas_municipais_es_32070322","inep_code":"32070322","name":"CEIM VALDIR GABRIEL MARIM","municipio":"Linhares","uf":"ES","status":"Em Atividade","address":"ALFREDO RIGONI, 30, PLANALTO","number":"30","district":"PLANALTO","postal_code":"29906-680","classification":"alta","georef_source":"INEP Tabela_Escola_2025.csv"},"escolas_municipais_es_32067755":{"id":"escolas_municipais_es_32067755","inep_code":"32067755","name":"CEIM VILA REGENCIA","municipio":"Linhares","uf":"ES","status":"Em Atividade","address":"RUA LIDIO DE OLIVEIRA, S/Nº","number":"S/Nº","postal_code":"29914-000","classification":"alta","georef_source":"INEP Tabela_Escola_2025.csv"},"escolas_municipais_es_32064560":{"id":"escolas_municipais_es_32064560","inep_code":"32064560","name":"CEIM VOVO AURORA","municipio":"Linhares","uf":"ES","status":"Em Atividade","address":"RUA LEOPOLDO MOREIRA, S/N","number":"S/N","postal_code":"29919-500","classification":"alta","georef_source":"INEP Tabela_Escola_2025.csv"},"escolas_municipais_es_32066970":{"id":"escolas_municipais_es_32066970","inep_code":"32066970","name":"CEIM WENDERSON NICO DE FREITAS","municipio":"Linhares","uf":"ES","status":"Em Atividade","address":"ALEXANDRE ZUEQUETTO, S/N, PROXIMO DO CAMPO, FARIAS","number":"S/N","district":"FARIAS","postal_code":"29911-020","classification":"alta","georef_source":"INEP Tabela_Escola_2025.csv"},"escolas_municipais_es_32122004":{"id":"escolas_municipais_es_32122004","inep_code":"32122004","name":"CMEIEF ALCIDES MARINATO","municipio":"Linhares","uf":"ES","status":"Em Atividade","address":"RUA PRINCIPAL DA BAGUEIRA, S/N, BAGUEIRA","number":"S/N","district":"BAGUEIRA","postal_code":"29918-899","classification":"alta","georef_source":"INEP Tabela_Escola_2025.csv"},"escolas_municipais_es_32024614":{"id":"escolas_municipais_es_32024614","inep_code":"32024614","name":"CMEIEFTI BOA ESPERANCA","municipio":"Linhares","uf":"ES","status":"Em Atividade","address":"RURAL, SN, AREA RURAL, AREA RURAL DE LINHARES","number":"SN","district":"AREA RURAL DE LINHARES","postal_code":"29918-899","classification":"alta","georef_source":"INEP Tabela_Escola_2025.csv"},"escolas_municipais_es_32083165":{"id":"escolas_municipais_es_32083165","inep_code":"32083165","name":"CMEIEFTI PALMITAL","municipio":"Linhares","uf":"ES","status":"Em Atividade","address":"RUA COELHO NETO, S/N, PALMITAL","number":"S/N","district":"PALMITAL","postal_code":"29906-765","classification":"alta","georef_source":"INEP Tabela_Escola_2025.csv"},"escolas_municipais_es_32097808":{"id":"escolas_municipais_es_32097808","inep_code":"32097808","name":"EMEF ADELSON DEL SANTO","municipio":"Linhares","uf":"ES","status":"Em Atividade","address":"LAGOA BONITA, SN, NOVA ESPERANÇA","number":"SN","district":"NOVA ESPERANÇA","postal_code":"29908-635","classification":"alta","georef_source":"INEP Tabela_Escola_2025.csv"},"escolas_municipais_es_32022786":{"id":"escolas_municipais_es_32022786","inep_code":"32022786","name":"EMEF ANGELO RECLA","municipio":"Linhares","uf":"ES","status":"Em Atividade","address":"AVENIDA SANTA LUZIA, S/Nº, RIO QUARTEL","number":"S/Nº","district":"RIO QUARTEL","postal_code":"29913-315","classification":"alta","georef_source":"INEP Tabela_Escola_2025.csv"},"escolas_municipais_es_32021909":{"id":"escolas_municipais_es_32021909","inep_code":"32021909","name":"EMEF ANTONIO FERNANDES DE ALMEIDA","municipio":"Linhares","uf":"ES","status":"Em Atividade","address":"ANTONIO FERNANDES DE ALMEIDA, S/N, INTERLAGOS","number":"S/N","district":"INTERLAGOS","postal_code":"29903-161","classification":"alta","georef_source":"INEP Tabela_Escola_2025.csv"},"escolas_municipais_es_32021925":{"id":"escolas_municipais_es_32021925","inep_code":"32021925","name":"EMEF AUTO GUIMARAES E SOUZA","municipio":"Linhares","uf":"ES","status":"Em Atividade","address":"ARACRUZ, 153, SHELL","number":"153","district":"SHELL","postal_code":"29901-520","classification":"alta","georef_source":"INEP Tabela_Escola_2025.csv"},"escolas_municipais_es_32022476":{"id":"escolas_municipais_es_32022476","inep_code":"32022476","name":"EMEF CABOCLO BERNARDO","municipio":"Linhares","uf":"ES","status":"Em Atividade","address":"RUA HONORATO DA ROSA, S/N, PLANALTO","number":"S/N","district":"PLANALTO","postal_code":"29906-630","classification":"alta","georef_source":"INEP Tabela_Escola_2025.csv"},"escolas_municipais_es_32022760":{"id":"escolas_municipais_es_32022760","inep_code":"32022760","name":"EMEF CELINA COUTINHO NUNES","municipio":"Linhares","uf":"ES","status":"Em Atividade","address":"LAGOA DO AGUIAR, S/N, RUA PRINCIPAL, BAIXO QUARTEL","number":"S/N","district":"BAIXO QUARTEL","postal_code":"29913-400","classification":"alta","georef_source":"INEP Tabela_Escola_2025.csv"},"escolas_municipais_es_32021968":{"id":"escolas_municipais_es_32021968","inep_code":"32021968","name":"EMEF CID ADALBERTO DOS REIS","municipio":"Linhares","uf":"ES","status":"Em Atividade","address":"RUA VALDOMIRO CARDOSO, S/N, JUPARANA","number":"S/N","district":"JUPARANA","postal_code":"29900-800","classification":"alta","georef_source":"INEP Tabela_Escola_2025.csv"},"escolas_municipais_es_32021992":{"id":"escolas_municipais_es_32021992","inep_code":"32021992","name":"EMEF DINORAH ALMEIDA RODRIGUES","municipio":"Linhares","uf":"ES","status":"Em Atividade","address":"JOAO EVANILDO MARIM, SN, QUADRA 64, SÃO JOSÉ","number":"SN","district":"SÃO JOSÉ","postal_code":"29905-090","classification":"alta","georef_source":"INEP Tabela_Escola_2025.csv"},"escolas_municipais_es_32022018":{"id":"escolas_municipais_es_32022018","inep_code":"32022018","name":"EMEF ELZA RONI SCARPATI","municipio":"Linhares","uf":"ES","status":"Em Atividade","address":"CARIJOS, SN, LAGOA DO MEIO","number":"SN","district":"LAGOA DO MEIO","postal_code":"29904-140","classification":"alta","georef_source":"INEP Tabela_Escola_2025.csv"},"escolas_municipais_es_32022042":{"id":"escolas_municipais_es_32022042","inep_code":"32022042","name":"EMEF JERONIMO MONTEIRO","municipio":"Linhares","uf":"ES","status":"Em Atividade","address":"PRESIDENTE COSTA E SILVA, SN, NOVO HORIZONTE","number":"SN","district":"NOVO HORIZONTE","postal_code":"29902-120","classification":"alta","georef_source":"INEP Tabela_Escola_2025.csv"},"escolas_municipais_es_32021950":{"id":"escolas_municipais_es_32021950","inep_code":"32021950","name":"EMEF JOSE MODENEZE","municipio":"Linhares","uf":"ES","status":"Em Atividade","address":"ARLINDO GAMA, CANIVETE","district":"CANIVETE","postal_code":"29909-260","classification":"alta","georef_source":"INEP Tabela_Escola_2025.csv"},"escolas_municipais_es_32022069":{"id":"escolas_municipais_es_32022069","inep_code":"32022069","name":"EMEF LUIZ DE CAMOES","municipio":"Linhares","uf":"ES","status":"Em Atividade","address":"AVENIDA CELESTE FAE, 1218, NOSSA SENHORA DA CONCEICAO","number":"1218","district":"NOSSA SENHORA DA CONCEICAO","postal_code":"29900-526","classification":"alta","georef_source":"INEP Tabela_Escola_2025.csv"},"escolas_municipais_es_32023618":{"id":"escolas_municipais_es_32023618","inep_code":"32023618","name":"EMEF MANOEL MARTINS","municipio":"Linhares","uf":"ES","status":"Em Atividade","address":"AVENIDA JUPTER, S/N, SN, PONTAL DO IPIRANGA","number":"SN","district":"PONTAL DO IPIRANGA","postal_code":"29900-994","classification":"alta","georef_source":"INEP Tabela_Escola_2025.csv"},"escolas_municipais_es_32080212":{"id":"escolas_municipais_es_32080212","inep_code":"32080212","name":"EMEF MARIA SOUZA MATIAS","municipio":"Linhares","uf":"ES","status":"Em Atividade","address":"RUA JATOBA, S/N, MOVELAR","number":"S/N","district":"MOVELAR","postal_code":"29906-150","classification":"alta","georef_source":"INEP Tabela_Escola_2025.csv"},"escolas_municipais_es_32022204":{"id":"escolas_municipais_es_32022204","inep_code":"32022204","name":"EMEF NOSSA SENHORA DA CONCEICAO","municipio":"Linhares","uf":"ES","status":"Em Atividade","address":"SAO PAULO, 28, AVISO","number":"28","district":"AVISO","postal_code":"29901-150","classification":"alta","georef_source":"INEP Tabela_Escola_2025.csv"},"escolas_municipais_es_32022956":{"id":"escolas_municipais_es_32022956","inep_code":"32022956","name":"EMEF OROZIMBO LEITE","municipio":"Linhares","uf":"ES","status":"Em Atividade","address":"GERALDO BOBBIO, 00, ZONA RURAL, GUAXE","number":"00","district":"GUAXE","postal_code":"29911-200","classification":"alta","georef_source":"INEP Tabela_Escola_2025.csv"},"escolas_municipais_es_32022107":{"id":"escolas_municipais_es_32022107","inep_code":"32022107","name":"EMEF PREFEITO ROBERTO CALMON","municipio":"Linhares","uf":"ES","status":"Em Atividade","address":"MARANHAO, SN, AVISO","number":"SN","district":"AVISO","postal_code":"29901-250","classification":"alta","georef_source":"INEP Tabela_Escola_2025.csv"},"escolas_municipais_es_32022115":{"id":"escolas_municipais_es_32022115","inep_code":"32022115","name":"EMEF PRESIDENTE CASTELO BRANCO","municipio":"Linhares","uf":"ES","status":"Em Atividade","address":"VISTA ALEGRE, S/Nº, CENTRO","number":"S/Nº","district":"CENTRO","postal_code":"29900-330","classification":"alta","georef_source":"INEP Tabela_Escola_2025.csv"},"escolas_municipais_es_32023030":{"id":"escolas_municipais_es_32023030","inep_code":"32023030","name":"EMEF PROF EFIGENIA SIZENANDO","municipio":"Linhares","uf":"ES","status":"Em Atividade","address":"JOAO SOPRANI, S/N, FARIAS","number":"S/N","district":"FARIAS","postal_code":"29911-015","classification":"alta","georef_source":"INEP Tabela_Escola_2025.csv"},"escolas_municipais_es_32084293":{"id":"escolas_municipais_es_32084293","inep_code":"32084293","name":"EMEF PROFESSOR JOCIVAL MARCHIORI","municipio":"Linhares","uf":"ES","status":"Em Atividade","address":"JOSE TURI, S N, RESIDENCIAL RIO DOCE, AVISO","number":"S N","district":"AVISO","postal_code":"29901-381","classification":"media","georef_source":"google_geocoding_api"},"escolas_municipais_es_32022131":{"id":"escolas_municipais_es_32022131","inep_code":"32022131","name":"EMEF PROFESSORA MARIA APARECIDA LAVAGNOLI","municipio":"Linhares","uf":"ES","status":"Em Atividade","address":"REPUBLICA, 521, INTERLAGOS","number":"521","district":"INTERLAGOS","postal_code":"29903-515","classification":"alta","georef_source":"INEP Tabela_Escola_2025.csv"},"escolas_municipais_es_32022034":{"id":"escolas_municipais_es_32022034","inep_code":"32022034","name":"EMEF PROFESSORA MARIA DA PENHA PAZITO VENTURA","municipio":"Linhares","uf":"ES","status":"Em Atividade","address":"MARTIN AFONSO DE SOUZA, SN, CASA, INTERLAGOS","number":"SN","district":"INTERLAGOS","postal_code":"29903-035","classification":"alta","georef_source":"INEP Tabela_Escola_2025.csv"},"escolas_municipais_es_32023669":{"id":"escolas_municipais_es_32023669","inep_code":"32023669","name":"EMEF PROFESSORA URBANA PENHA COSTA","municipio":"Linhares","uf":"ES","status":"Em Atividade","address":"RUA BERESFORD MARTINS MORREIRA, S/N, S/N, PREDIO","number":"S/N","postal_code":"29900-995","classification":"alta","georef_source":"INEP Tabela_Escola_2025.csv"},"escolas_municipais_es_32022816":{"id":"escolas_municipais_es_32022816","inep_code":"32022816","name":"EMEF PROFª ELIANA CORREA PINAFO","municipio":"Linhares","uf":"ES","status":"Em Atividade","address":"AVENIDA LUIZ DEL CARO, 56, BEBEDOURO","number":"56","district":"BEBEDOURO","postal_code":"29913-180","classification":"alta","georef_source":"INEP Tabela_Escola_2025.csv"},"escolas_municipais_es_32022174":{"id":"escolas_municipais_es_32022174","inep_code":"32022174","name":"EMEF ROBERTO MOREIRA","municipio":"Linhares","uf":"ES","status":"Em Atividade","address":"SANTOS DUMONT, SNº, ARAÇÁ","number":"SNº","district":"ARAÇÁ","postal_code":"29901-445","classification":"alta","georef_source":"INEP Tabela_Escola_2025.csv"},"escolas_municipais_es_32064730":{"id":"escolas_municipais_es_32064730","inep_code":"32064730","name":"EMEF SAMUEL BATISTA CRUZ","municipio":"Linhares","uf":"ES","status":"Em Atividade","address":"RUA PINHEIROS, S/N, INTERLAGOS","number":"S/N","district":"INTERLAGOS","postal_code":"29903-053","classification":"alta","georef_source":"INEP Tabela_Escola_2025.csv"},"escolas_municipais_es_32022336":{"id":"escolas_municipais_es_32022336","inep_code":"32022336","name":"EMEF TALMA DRUMOND PESTANA","municipio":"Linhares","uf":"ES","status":"Em Atividade","address":"AVENIDA MANOEL BANDEIRA, 527, PALMITAL","number":"527","district":"PALMITAL","postal_code":"29906-810","classification":"alta","georef_source":"INEP Tabela_Escola_2025.csv"},"escolas_municipais_es_32022182":{"id":"escolas_municipais_es_32022182","inep_code":"32022182","name":"EMEF ZEFERINO BATISTA FIOROT","municipio":"Linhares","uf":"ES","status":"Em Atividade","address":"ADEMAR LUIZ PIANA, SN, SANTA CRUZ","number":"SN","district":"SANTA CRUZ","postal_code":"29908-032","classification":"alta","georef_source":"INEP Tabela_Escola_2025.csv"},"escolas_municipais_es_32022190":{"id":"escolas_municipais_es_32022190","inep_code":"32022190","name":"EMEFM MARILIA DE REZENDE SCARTON COUTINHO","municipio":"Linhares","uf":"ES","status":"Em Atividade","address":"QUINTINO BOCAIUVA, 1205, INTERLAGOS","number":"1205","district":"INTERLAGOS","postal_code":"29903-059","classification":"alta","georef_source":"INEP Tabela_Escola_2025.csv"},"escolas_municipais_es_32023707":{"id":"escolas_municipais_es_32023707","inep_code":"32023707","name":"EMPEF JOSE CANDIDO DURAO","municipio":"Linhares","uf":"ES","status":"Em Atividade","address":"RURAL, ÁREA RURAL DE LINHARES","district":"ÁREA RURAL DE LINHARES","postal_code":"29918-899","classification":"alta","georef_source":"INEP Tabela_Escola_2025.csv"},"escolas_municipais_es_32022735":{"id":"escolas_municipais_es_32022735","inep_code":"32022735","name":"EMPEF PALHAL","municipio":"Linhares","uf":"ES","status":"Em Atividade","address":"RURAL, BEBEDOURO, ÁREA RURAL DE LINHARES","district":"ÁREA RURAL DE LINHARES","postal_code":"29918-899","classification":"alta","georef_source":"INEP Tabela_Escola_2025.csv"},"escolas_municipais_es_32024851":{"id":"escolas_municipais_es_32024851","inep_code":"32024851","name":"EMPEF PATRIMONIO DO HUMAITA","municipio":"Linhares","uf":"ES","status":"Em Atividade","address":"RURAL, ÁREA RURAL DE LINHARES","district":"ÁREA RURAL DE LINHARES","postal_code":"29918-899","classification":"alta","georef_source":"INEP Tabela_Escola_2025.csv"},"escolas_municipais_es_32098006":{"id":"escolas_municipais_es_32098006","inep_code":"32098006","name":"EMPEF VILA BETHANIA","municipio":"Linhares","uf":"ES","status":"Em Atividade","address":"JOSE DOANO, S/N, NOVA BETÂNIA","number":"S/N","district":"NOVA BETÂNIA","postal_code":"29907-550","classification":"alta","georef_source":"INEP Tabela_Escola_2025.csv"},"escolas_municipais_es_32077882":{"id":"escolas_municipais_es_32077882","inep_code":"32077882","name":"EMPEI GERONCIO FRANCISCO","municipio":"Linhares","uf":"ES","status":"Em Atividade","address":"PATRIMONIO DO HUMAITA, SN, ÁREA RURAL DE LINHARES","number":"SN","district":"ÁREA RURAL DE LINHARES","postal_code":"29918-899","classification":"alta","georef_source":"INEP Tabela_Escola_2025.csv"},"escolas_municipais_es_32082428":{"id":"escolas_municipais_es_32082428","inep_code":"32082428","name":"EMPEI PAULO DAMIAO TRISTAO PURINHA","municipio":"Linhares","uf":"ES","status":"Em Atividade","address":"ASSENTAMENTO SEZINIO FERNANDES DE JESUS, SN, PATRIMONIO HUMAITA, AREA RURAL DE LINHARES","number":"SN","district":"AREA RURAL DE LINHARES","postal_code":"29918-899","classification":"alta","georef_source":"INEP Tabela_Escola_2025.csv"},"escolas_municipais_es_32023880":{"id":"escolas_municipais_es_32023880","inep_code":"32023880","name":"EMPEIPEF AREAL","municipio":"Linhares","uf":"ES","status":"Em Atividade","address":"RURAL, SN, AREA RURAL DE LINHARES","number":"SN","district":"AREA RURAL DE LINHARES","postal_code":"29918-899","classification":"alta","georef_source":"INEP Tabela_Escola_2025.csv"},"escolas_municipais_es_32023634":{"id":"escolas_municipais_es_32023634","inep_code":"32023634","name":"EMPEIPEF BANANAL DO SUL","municipio":"Linhares","uf":"ES","status":"Em Atividade","address":"RURAL, SN, ÁREA RURAL DE LINHARES","number":"SN","district":"ÁREA RURAL DE LINHARES","postal_code":"29918-899","classification":"alta","georef_source":"INEP Tabela_Escola_2025.csv"},"escolas_municipais_es_32023472":{"id":"escolas_municipais_es_32023472","inep_code":"32023472","name":"EMPEIPEF BIBIANA COSTA","municipio":"Linhares","uf":"ES","status":"Em Atividade","address":"RURAL, S/N, ZONA RURAL, ÁREA RURAL DE LINHARES","number":"S/N","district":"ÁREA RURAL DE LINHARES","postal_code":"29918-899","classification":"alta","georef_source":"INEP Tabela_Escola_2025.csv"},"escolas_municipais_es_32024720":{"id":"escolas_municipais_es_32024720","inep_code":"32024720","name":"EMPEIPEF CORREGO DOUTOR JONES","municipio":"Linhares","uf":"ES","status":"Em Atividade","address":"RURAL, SN, CORREGO DR. JONES, AREA RURAL DE LINHARES","number":"SN","district":"AREA RURAL DE LINHARES","postal_code":"29918-899","classification":"alta","georef_source":"INEP Tabela_Escola_2025.csv"},"escolas_municipais_es_32024479":{"id":"escolas_municipais_es_32024479","inep_code":"32024479","name":"EMPEIPEF CORREGO JAPIRA","municipio":"Linhares","uf":"ES","status":"Em Atividade","address":"RURAL, S/N, CORREGO JAPIRA, ÁREA RURAL DE LINHARES","number":"S/N","district":"ÁREA RURAL DE LINHARES","postal_code":"29918-899","classification":"alta","georef_source":"INEP Tabela_Escola_2025.csv"},"escolas_municipais_es_32024703":{"id":"escolas_municipais_es_32024703","inep_code":"32024703","name":"EMPEIPEF CORREGO SAO PEDRO","municipio":"Linhares","uf":"ES","status":"Em Atividade","address":"RURAL, ÁREA RURAL DE LINHARES","district":"ÁREA RURAL DE LINHARES","postal_code":"29918-899","classification":"alta","georef_source":"INEP Tabela_Escola_2025.csv"},"escolas_municipais_es_32022840":{"id":"escolas_municipais_es_32022840","inep_code":"32022840","name":"EMPEIPEF FLORENTINO RODRIGUES BATISTA","municipio":"Linhares","uf":"ES","status":"Em Atividade","address":"RURAL, S/N, ESTRADA DE REGENCIA, ÁREA RURAL DE LINHARES","number":"S/N","district":"ÁREA RURAL DE LINHARES","postal_code":"29918-899","classification":"alta","georef_source":"INEP Tabela_Escola_2025.csv"},"escolas_municipais_es_32024738":{"id":"escolas_municipais_es_32024738","inep_code":"32024738","name":"EMPEIUEF EMA SARTORIO BIANCARDI","municipio":"Linhares","uf":"ES","status":"Em Atividade","address":"RURAL, S/N, ÁREA RURAL DE LINHARES","number":"S/N","district":"ÁREA RURAL DE LINHARES","postal_code":"29918-899","classification":"alta","georef_source":"INEP Tabela_Escola_2025.csv"},"escolas_municipais_es_32022905":{"id":"escolas_municipais_es_32022905","inep_code":"32022905","name":"EMPEIUEF RIO QUARTEL","municipio":"Linhares","uf":"ES","status":"Em Atividade","address":"RURAL, ÁREA RURAL DE LINHARES","district":"ÁREA RURAL DE LINHARES","postal_code":"29918-899","classification":"alta","georef_source":"INEP Tabela_Escola_2025.csv"},"escolas_municipais_es_32024916":{"id":"escolas_municipais_es_32024916","inep_code":"32024916","name":"EMPEIUEF TERRA ALTA","municipio":"Linhares","uf":"ES","status":"Em Atividade","address":"RURAL, SAO RAFAEL, AREA RURAL DE LINHARES","district":"AREA RURAL DE LINHARES","postal_code":"29918-899","classification":"alta","georef_source":"INEP Tabela_Escola_2025.csv"},"escolas_municipais_es_32024673":{"id":"escolas_municipais_es_32024673","inep_code":"32024673","name":"EMUEF CORREGO DO MEIO","municipio":"Linhares","uf":"ES","status":"Em Atividade","address":"AREA RURAL, SN, AREA RURAL DE LINHARES","number":"SN","district":"AREA RURAL DE LINHARES","postal_code":"29918-899","classification":"alta","georef_source":"INEP Tabela_Escola_2025.csv"},"escolas_municipais_es_32076118":{"id":"escolas_municipais_es_32076118","inep_code":"32076118","name":"EMUEF FAZENDA THESOURO","municipio":"Linhares","uf":"ES","status":"Em Atividade","address":"ZONA RURAL, S/N, CENTRO","number":"S/N","district":"CENTRO","postal_code":"29900-970","classification":"alta","georef_source":"INEP Tabela_Escola_2025.csv"},"escolas_municipais_es_32024770":{"id":"escolas_municipais_es_32024770","inep_code":"32024770","name":"EMUEF LAGOA DAS PALMAS","municipio":"Linhares","uf":"ES","status":"Em Atividade","address":"AREA RURAL, AREA RURAL DE LINHARES","district":"AREA RURAL DE LINHARES","postal_code":"29918-899","classification":"alta","georef_source":"INEP Tabela_Escola_2025.csv"},"escolas_municipais_es_32024509":{"id":"escolas_municipais_es_32024509","inep_code":"32024509","name":"EMUEF NOSSA SRA DO BOM PARTO","municipio":"Linhares","uf":"ES","status":"Em Atividade","address":"TERRA ALTA, AREA RURAL DE LINHARES","district":"AREA RURAL DE LINHARES","postal_code":"29918-899","classification":"alta","georef_source":"INEP Tabela_Escola_2025.csv"},"escolas_municipais_es_32022859":{"id":"escolas_municipais_es_32022859","inep_code":"32022859","name":"EMUEF PAULO ANDRE DE LIMA","municipio":"Linhares","uf":"ES","status":"Em Atividade","address":"AREA RURAL, AREA RURAL DE LINHARES","district":"AREA RURAL DE LINHARES","postal_code":"29918-899","classification":"alta","georef_source":"INEP Tabela_Escola_2025.csv"},"escolas_municipais_es_32023340":{"id":"escolas_municipais_es_32023340","inep_code":"32023340","name":"EMUEF PONTAL DO OURO","municipio":"Linhares","uf":"ES","status":"Em Atividade","address":"DISTRITO DO GUAXE, ÁREA RURAL DE LINHARES","district":"ÁREA RURAL DE LINHARES","postal_code":"29918-899","classification":"alta","georef_source":"INEP Tabela_Escola_2025.csv"},"escolas_municipais_es_32024010":{"id":"escolas_municipais_es_32024010","inep_code":"32024010","name":"EMUEF SANTA ROSA","municipio":"Linhares","uf":"ES","status":"Em Atividade","address":"AREA RURAL, SN, BREJO GRANDE, AREA RURAL DE LINHARES","number":"SN","district":"AREA RURAL DE LINHARES","postal_code":"29918-899","classification":"alta","georef_source":"INEP Tabela_Escola_2025.csv"},"escolas_municipais_es_32024894":{"id":"escolas_municipais_es_32024894","inep_code":"32024894","name":"EMUEF SAO JUDAS TADEU","municipio":"Linhares","uf":"ES","status":"Em Atividade","address":"RURAL, ÁREA RURAL DE LINHARES","district":"ÁREA RURAL DE LINHARES","postal_code":"29918-899","classification":"alta","georef_source":"INEP Tabela_Escola_2025.csv"}}}