{"shard":"alfredo-chaves","schools":{"school-23":{"id":"school-23","name":"school-23","municipio":"Alfredo Chaves","uf":"ES","email":"escolacamilamotta@sedu.es.gov.br"},"school-24":{"id":"school-24","name":"school-24","municipio":"Alfredo Chaves","uf":"ES"},"school-25":{"id":"school-25","name":"school-25","municipio":"Alfredo Chaves","uf":"ES"},"school-26":{"id":"school-26","name":"school-26","municipio":"Alfredo Chaves","uf":"ES"},"school-27":{"id":"school-27","name":"school-27","municipio":"Alfredo Chaves","uf":"ES"},"school-28":{"id":"school-28","name":"school-28","municipio":"Alfredo Chaves","uf":"ES"}}}