{"shard":"marilandia","schools":{"escolas_estaduais_es_32068344":{"id":"escolas_estaduais_es_32068344","inep_code":"32068344","name":"ESCOLA FAMILIA AGRICOLA DE MARILANDIA - MEPES","name_original":"ESCOLA FAMILIA AGRICOLA DE MARILANDIA - MEPES","municipio":"Marilandia","uf":"ES","status":"Em Atividade","address":"AVENIDA DOM BOSCO","number":"150","district":"CENTRO","postal_code":"29725-000","classification":"alta","georef_source":"google_geocoding_api","phone_primary":"(27) 3724-1019","email":"efamarilandia@yahoo.com.br"},"escolas_estaduais_es_32000034":{"id":"escolas_estaduais_es_32000034","inep_code":"32000034","name":"PRÉ-ENEM EEEFM PADRE ANTONIO VOLKERS","name_original":"PRÉ-ENEM EEEFM PADRE ANTONIO VOLKERS","municipio":"Marilandia","uf":"ES","status":"Em Atividade","address":"AVENIDA DOM BOSCO","number":"782","district":"CENTRO","postal_code":"29725-000","classification":"alta","georef_source":"google_geocoding_api","phone_primary":"(27) 3724-1741","email":"escolapadreantonio@sedu.es.gov.br","teacher_count":7},"escolas_estaduais_es_32012713":{"id":"escolas_estaduais_es_32012713","inep_code":"32012713","name":"EEEFM PADRE ANTONIO VOLKERS","name_original":"EEEFM PADRE ANTONIO VOLKERS","municipio":"Marilândia","uf":"ES","status":"Em Atividade","address":"AVENIDA DOM BOSCO","number":"782","district":"CENTRO","postal_code":"29725-000","classification":"alta","georef_source":"Catálogo de Escolas do INEP","phone_primary":"(27) 3724-1741","email":"escolapadreantonio@sedu.es.gov.br","teacher_count":55}}}