{"shard":"sao-mateus","schools":{"school-533":{"id":"school-533","name":"school-533","municipio":"Sao Mateus","uf":"ES","email":"escolaemilioroberto@sedu.es.gov.br"},"school-534":{"id":"school-534","name":"school-534","municipio":"Sao Mateus","uf":"ES","email":"escolaceciliano@sedu.es.gov.br"},"school-626":{"id":"school-626","name":"school-626","municipio":"São Mateus","uf":"ES","email":"escolamaritamotta@sedu.es.gov.br"},"school-627":{"id":"school-627","name":"school-627","municipio":"São Mateus","uf":"ES"},"school-628":{"id":"school-628","name":"school-628","municipio":"São Mateus","uf":"ES","email":"escolaegidiobordoni@sedu.es.gov.br"},"school-629":{"id":"school-629","name":"school-629","municipio":"São Mateus","uf":"ES","email":"escolaoutubro@sedu.es.gov.br"},"school-630":{"id":"school-630","name":"school-630","municipio":"São Mateus","uf":"ES","email":"escolaamerico@sedu.es.gov.br"},"school-631":{"id":"school-631","name":"school-631","municipio":"São Mateus","uf":"ES","email":"escolasantamaria@sedu.es.gov.br"},"school-632":{"id":"school-632","name":"school-632","municipio":"São Mateus","uf":"ES","email":"escolaemilioroberto@sedu.es.gov.br"},"school-633":{"id":"school-633","name":"school-633","municipio":"São Mateus","uf":"ES","email":"escolanestorgomes@sedu.es.gov.br"},"school-634":{"id":"school-634","name":"school-634","municipio":"São Mateus","uf":"ES","email":"escolapio12@sedu.es.gov.br"},"school-635":{"id":"school-635","name":"school-635","municipio":"São Mateus","uf":"ES","email":"escolasantoantonio@sedu.es.gov.br"},"school-636":{"id":"school-636","name":"school-636","municipio":"São Mateus","uf":"ES","email":"escolawallacecastelo@sedu.es.gov.br"},"school-637":{"id":"school-637","name":"school-637","municipio":"São Mateus","uf":"ES","email":"escolasetembro@sedu.es.gov.br"},"school-638":{"id":"school-638","name":"school-638","municipio":"São Mateus","uf":"ES","email":"escolaceciliano@sedu.es.gov.br"},"school-639":{"id":"school-639","name":"school-639","municipio":"São Mateus","uf":"ES"},"school-640":{"id":"school-640","name":"school-640","municipio":"São Mateus","uf":"ES"},"school-641":{"id":"school-641","name":"school-641","municipio":"São Mateus","uf":"ES"},"school-642":{"id":"school-642","name":"school-642","municipio":"São Mateus","uf":"ES"},"school-643":{"id":"school-643","name":"school-643","municipio":"São Mateus","uf":"ES"},"school-644":{"id":"school-644","name":"school-644","municipio":"São Mateus","uf":"ES"},"school-645":{"id":"school-645","name":"school-645","municipio":"São Mateus","uf":"ES"},"school-646":{"id":"school-646","name":"school-646","municipio":"São Mateus","uf":"ES","email":"escolapadreezequiel@sedu.es.gov.br"},"school-647":{"id":"school-647","name":"school-647","municipio":"São Mateus","uf":"ES"},"school-648":{"id":"school-648","name":"school-648","municipio":"São Mateus","uf":"ES","email":"escolavalevitoria@sedu.es.gov.br"},"school-649":{"id":"school-649","name":"school-649","municipio":"São Mateus","uf":"ES"},"school-650":{"id":"school-650","name":"school-650","municipio":"São Mateus","uf":"ES"},"school-651":{"id":"school-651","name":"school-651","municipio":"São Mateus","uf":"ES"},"school-652":{"id":"school-652","name":"school-652","municipio":"São Mateus","uf":"ES"},"school-653":{"id":"school-653","name":"school-653","municipio":"São Mateus","uf":"ES"},"school-654":{"id":"school-654","name":"school-654","municipio":"São Mateus","uf":"ES"},"school-655":{"id":"school-655","name":"school-655","municipio":"São Mateus","uf":"ES"},"school-656":{"id":"school-656","name":"school-656","municipio":"São Mateus","uf":"ES"},"school-657":{"id":"school-657","name":"school-657","municipio":"São Mateus","uf":"ES"},"school-658":{"id":"school-658","name":"school-658","municipio":"São Mateus","uf":"ES"},"school-659":{"id":"school-659","name":"school-659","municipio":"São Mateus","uf":"ES"}}}