{"z":15,"x":12733,"y":18164,"features":[{"k":"s","i":"escolas_municipais_es_32064551","x":-40.10252,"y":-19.19107,"n":"CEIM AURORA NUNES DE OLIVEIRA","t":24,"d":"sooretama"},{"k":"s","i":"escolas_municipais_es_32078994","x":-40.10944,"y":-19.19088,"n":"EMEF ALVARO MARQUES DE OLIVEIRA","t":48,"d":"sooretama"},{"k":"s","i":"escolas_municipais_es_32080905","x":-40.109534,"y":-19.191723,"n":"CEIM ANIZIO ALMEIDA","t":28,"d":"sooretama"},{"k":"s","i":"escolas_municipais_es_32114001","x":-40.102828,"y":-19.190283,"n":"CENTRO DE DESENVOLVIMENTO EDUCACIONAL IRMA MICHELA NARCHI- ESCOLA DO FUTURO","t":0,"d":"sooretama"}]}