{"z":13,"x":3169,"y":4580,"features":[{"k":"c","i":"c-13-12677-18323","x":-40.722017,"y":-20.832931,"p":4,"b":[-40.724249,-20.83547,-40.719158,-20.82918]},{"k":"s","i":"school-1407","x":-40.731849,"y":-20.83631,"n":"school-1407","d":"piuma"},{"k":"s","i":"school-1410","x":-40.719477,"y":-20.827889,"n":"school-1410","d":"piuma"},{"k":"s","i":"school-1418","x":-40.71418,"y":-20.83617,"n":"school-1418","d":"piuma"},{"k":"s","i":"school-99","x":-40.694454,"y":-20.830277,"n":"school-99","d":"anchieta"}]}