{"z":14,"x":6354,"y":9137,"features":[{"k":"s","i":"escolas_estaduais_es_32034563","x":-40.373108,"y":-20.338551,"n":"EEEF ANTONIO ESTEVES","t":12,"d":"cariacica"},{"k":"s","i":"escolas_estaduais_es_32034784","x":-40.381447,"y":-20.332693,"n":"EEEFM NOSSA SENHORA APARECIDA","t":31,"d":"cariacica"},{"k":"s","i":"escolas_estaduais_es_32034857","x":-40.374309,"y":-20.326407,"n":"CEEFMTI PROFESSORA MARIA PENEDO","t":52,"d":"cariacica"},{"k":"s","i":"escolas_estaduais_es_32035020","x":-40.365874,"y":-20.337802,"n":"EEEFM DR AFONSO SCHWAB","t":38,"d":"cariacica"},{"k":"s","i":"escolas_estaduais_es_32035063","x":-40.36825,"y":-20.329474,"n":"EEEFM PROF MARIA DE LOURDES SANTOS SILVA","t":49,"d":"cariacica"}]}