{"z":12,"x":1584,"y":2281,"features":[{"k":"s","i":"escolas_municipais_es_32032226","x":-40.738023,"y":-20.082271,"n":"EMPEIEF RIO DAS PEDRAS","t":5,"d":"santa-maria-de-jetiba"},{"k":"s","i":"escolas_municipais_es_32032323","x":-40.708123,"y":-20.108214,"n":"EMUEF JOAO GUILHERME GERMANO BORCHARDT","t":5,"d":"santa-maria-de-jetiba"},{"k":"s","i":"escolas_municipais_es_32032331","x":-40.748414,"y":-20.111051,"n":"EMUEF ALBERTO SCHULZ","t":4,"d":"santa-maria-de-jetiba"},{"k":"s","i":"escolas_municipais_es_32032668","x":-40.773836,"y":-20.111354,"n":"EMUEF ALTO RIO TRIUNFO","t":5,"d":"santa-maria-de-jetiba"}]}