{"z":15,"x":12737,"y":18183,"features":[{"k":"s","i":"escolas_municipais_es_32021925","x":-40.062525,"y":-19.388922,"n":"EMEF AUTO GUIMARAES E SOUZA","t":19,"d":"linhares"},{"k":"s","i":"escolas_municipais_es_32022913","x":-40.066105,"y":-19.384577,"n":"CEIM DOCE MEL","t":10,"d":"linhares"},{"k":"s","i":"escolas_municipais_es_32064730","x":-40.05719,"y":-19.391037,"n":"EMEF SAMUEL BATISTA CRUZ","t":41,"d":"linhares"},{"k":"s","i":"escolas_municipais_es_32073925","x":-40.057074,"y":-19.390694,"n":"CEIM CRESCER","t":24,"d":"linhares"},{"k":"s","i":"escolas_municipais_es_32078013","x":-40.063703,"y":-19.390588,"n":"CEIM GENY RIBEIRO DE SOUZA","t":25,"d":"linhares"}]}