{"z":12,"x":1588,"y":2285,"features":[{"k":"c","i":"c-12-6354-9140","x":-40.371899,"y":-20.391218,"p":4,"b":[-40.375056,-20.395058,-40.36604,-20.388739]},{"k":"c","i":"c-12-6355-9142","x":-40.354038,"y":-20.439844,"p":9,"b":[-40.363276,-20.445178,-40.345201,-20.431793]},{"k":"s","i":"escolas_municipais_es_32039530","x":-40.342743,"y":-20.451892,"n":"UMEF PROFª MARIA DA GLORIA DE FREITAS DUARTE","t":16,"d":"vila-velha"},{"k":"s","i":"escolas_municipais_es_32063709","x":-40.364461,"y":-20.430819,"n":"UMEF PROF PAULO CESAR VINHA","t":76,"d":"vila-velha"}]}