{"z":13,"x":3191,"y":4526,"features":[{"k":"c","i":"c-13-12765-18104","x":-39.753755,"y":-18.569542,"p":2,"b":[-39.755604,-18.570189,-39.751905,-18.568895]},{"k":"c","i":"c-13-12767-18106","x":-39.732365,"y":-18.5893,"p":2,"b":[-39.733206,-18.589605,-39.731525,-18.588994]},{"k":"s","i":"school-614","x":-39.738634,"y":-18.583102,"n":"school-614","d":"conceicao-da-barra"},{"k":"s","i":"school-616","x":-39.739836,"y":-18.586715,"n":"school-616","d":"conceicao-da-barra"},{"k":"s","i":"school-629","x":-39.731687,"y":-18.570153,"n":"school-629","d":"conceicao-da-barra"},{"k":"s","i":"school-635","x":-39.730513,"y":-18.595138,"n":"school-635","d":"conceicao-da-barra"}]}