{"z":14,"x":6382,"y":9060,"features":[{"k":"c","i":"c-14-25528-36240","x":-39.766447,"y":-18.730182,"p":2,"b":[-39.766728,-18.730532,-39.766167,-18.729832]},{"k":"s","i":"school-1779","x":-39.757733,"y":-18.74557,"n":"school-1779","d":"sao-mateus"},{"k":"s","i":"school-1790","x":-39.759789,"y":-18.738138,"n":"school-1790","d":"sao-mateus"},{"k":"s","i":"school-1799","x":-39.754412,"y":-18.736554,"n":"school-1799","d":"sao-mateus"},{"k":"s","i":"school-1829","x":-39.750035,"y":-18.74509,"n":"school-1829","d":"sao-mateus"}]}