{"z":14,"x":6356,"y":9136,"features":[{"k":"c","i":"c-14-25424-36547","x":-40.340339,"y":-20.321083,"p":2,"b":[-40.340565,-20.321187,-40.340113,-20.320978],"h":[[2,1],[55,1]]},{"k":"c","i":"c-14-25427-36546","x":-40.324523,"y":-20.318245,"p":2,"b":[-40.324652,-20.318273,-40.324393,-20.318217],"h":[[3,1],[93,1]]},{"k":"s","i":"escolas_estaduais_es_32039972","x":-40.335512,"y":-20.31815,"n":"CEEJA - DE VITORIA","t":32,"d":"vitoria"},{"k":"s","i":"escolas_estaduais_es_32040288","x":-40.330165,"y":-20.317757,"n":"EEEM GOMES CARDIM","t":15,"d":"vitoria"},{"k":"s","i":"escolas_estaduais_es_32040881","x":-40.336926,"y":-20.31839,"n":"EEEF - ABERTA LAR D JOAO BATISTA","d":"vitoria"}]}