{"z":15,"x":12708,"y":18271,"features":[{"k":"s","i":"escolas_municipais_es_32033729","x":-40.376136,"y":-20.301187,"n":"EMEF ANTONIO COUTINHO OLIVEIRA","t":22,"d":"cariacica"},{"k":"s","i":"escolas_municipais_es_32074654","x":-40.383293,"y":-20.293589,"n":"EMEF AGUSTINHA MUNIZ DE OLIVEIRA","t":24,"d":"cariacica"},{"k":"s","i":"escolas_municipais_es_32077378","x":-40.376169,"y":-20.301771,"n":"CMEI PASTOR JOCARLY ALVES CARDOSO","t":27,"d":"cariacica"},{"k":"s","i":"escolas_municipais_es_32102208","x":-40.381208,"y":-20.295762,"n":"CMEI IVAN ROBERTO DE SOUSA","t":15,"d":"cariacica"}]}